Metadata-Version: 2.2
Name: latest-user-agents
Version: 0.0.5
Summary: Get the latest user agent strings for major browsers and OSs
Author-email: Jonathan Robson <jnrbsn@gmail.com>
Project-URL: Repository, https://github.com/jnrbsn/python-latest-user-agents
Classifier: Development Status :: 5 - Production/Stable
Classifier: License :: OSI Approved :: MIT License
Classifier: Programming Language :: Python :: 3
Classifier: Programming Language :: Python :: 3 :: Only
Classifier: Programming Language :: Python :: 3.9
Classifier: Programming Language :: Python :: 3.10
Classifier: Programming Language :: Python :: 3.11
Classifier: Programming Language :: Python :: 3.12
Classifier: Programming Language :: Python :: 3.13
Classifier: Topic :: Internet :: WWW/HTTP
License-File: LICENSE
Requires-Dist: platformdirs
Requires-Dist: requests
Provides-Extra: test
Requires-Dist: flake8; extra == "test"
Requires-Dist: flake8-bugbear; extra == "test"
Requires-Dist: flake8-commas; extra == "test"
Requires-Dist: flake8-isort; extra == "test"
Requires-Dist: flake8-pyproject; extra == "test"
Requires-Dist: flake8-quotes; extra == "test"
Requires-Dist: freezegun; extra == "test"
Requires-Dist: pytest; extra == "test"
Requires-Dist: pytest-cov; extra == "test"
Requires-Dist: pytest-mock; extra == "test"
